Metadata-Version: 2.1
Name: data2Insights
Version: 1.0
Summary: Data2Insights package
Home-page: UNKNOWN
Author: Deepika
Author-email: <mekalabhagyadeepika@gmail.com>
License: UNKNOWN
Keywords: Data2Insights,services,Text,Vision,Batch
Platform: UNKNOWN
Classifier: Development Status :: 1 - Planning
Classifier: Intended Audience :: Developers
Classifier: Programming Language :: Python :: 3
Classifier: Operating System :: Unix
Classifier: Operating System :: MacOS :: MacOS X
Classifier: Operating System :: Microsoft :: Windows
